xzqhotspot/__init__.py
xzqhotspot-3.1.0.dist-info/METADATA
xzqhotspot-3.1.0.dist-info/WHEEL
xzqhotspot-3.1.0.dist-info/top_level.txt
xzqhotspot-3.1.0.dist-info/RECORD
