Metadata-Version: 2.1
Name: xzqhotspot
Version: 3.1.0
Summary: Mobile Hotspot Manager for Win10
Home-page: UNKNOWN
Author: XZQ
Author-email: 690933685@qq.com
License: UNKNOWN
Platform: UNKNOWN
Requires-Python: >=3.7
Requires-Dist: winrt
Requires-Dist: pythonnet
Requires-Dist: pywifi
